xia_engine_rest/__init__.py
xia_engine_rest/engine.cp311-win_amd64.pyd
xia_engine_rest-0.1.15.dist-info/LICENSE.txt
xia_engine_rest-0.1.15.dist-info/METADATA
xia_engine_rest-0.1.15.dist-info/WHEEL
xia_engine_rest-0.1.15.dist-info/top_level.txt
xia_engine_rest-0.1.15.dist-info/RECORD
